seaborn/__init__.py
seaborn/algorithms.py
seaborn/apionly.py
seaborn/axisgrid.py
seaborn/categorical.py
seaborn/cm.py
seaborn/conftest.py
seaborn/distributions.py
seaborn/linearmodels.py
seaborn/matrix.py
seaborn/miscplot.py
seaborn/palettes.py
seaborn/rcmod.py
seaborn/regression.py
seaborn/relational.py
seaborn/timeseries.py
seaborn/utils.py
seaborn/widgets.py
seaborn/colors/__init__.py
seaborn/colors/crayons.py
seaborn/colors/xkcd_rgb.py
seaborn/external/__init__.py
seaborn/external/husl.py
seaborn/external/six.py
seaborn/tests/__init__.py
seaborn/tests/test_algorithms.py
seaborn/tests/test_axisgrid.py
seaborn/tests/test_categorical.py
seaborn/tests/test_distributions.py
seaborn/tests/test_matrix.py
seaborn/tests/test_miscplot.py
seaborn/tests/test_palettes.py
seaborn/tests/test_rcmod.py
seaborn/tests/test_regression.py
seaborn/tests/test_relational.py
seaborn/tests/test_utils.py
seaborn-0.10.1.dist-info/LICENSE
seaborn-0.10.1.dist-info/METADATA
seaborn-0.10.1.dist-info/WHEEL
seaborn-0.10.1.dist-info/top_level.txt
seaborn-0.10.1.dist-info/RECORD
